[
    {
        "id_documento": "12580",
        "pagina": 499,
        "nome_original": "senha.docx",
        "arquivo": "38_53_11032020063125_senha.docx",
        "extensao": ".docx",
        "pasta": "emailsenhamidia",
        "caminho": "https://10.100.77.20/xpertis/App/Lib/arquivos/documentos/emailsenhamidia/38_53_11032020063125_senha.docx",
        "erro": "Falha ao processar 38_53_11032020063125_senha.docx: Arquivo com conteúdo vazio",
        "arquivo_existe": 1,
        "data_insercao": "2024-12-02 15:13:46"
    }
]