[
    {
        "id_documento": "12080",
        "pagina": 479,
        "nome_original": "anexos.zip",
        "arquivo": "40_29_09032020131435_anexos.zip",
        "extensao": ".zip",
        "pasta": "ctvivo",
        "caminho": "https://10.100.77.20/xpertis/App/Lib/arquivos/documentos/ctvivo/40_29_09032020131435_anexos.zip",
        "erro": "Arquivo inexistente",
        "arquivo_existe": 1,
        "data_insercao": "2024-12-02 14:54:45"
    },
    {
        "id_documento": "12081",
        "pagina": 479,
        "nome_original": "OFÍCIO 212.19 - DERPOL ITABAIANA - SINESP.doc",
        "arquivo": "24_5_09032020131832_oficio212.19derpolitabaianasinesp.doc",
        "extensao": ".doc",
        "pasta": "oficiosadministrativos",
        "caminho": "https://10.100.77.20/xpertis/App/Lib/arquivos/documentos/oficiosadministrativos/24_5_09032020131832_oficio212.19derpolitabaianasinesp.doc",
        "erro": "Arquivo inexistente",
        "arquivo_existe": 0,
        "data_insercao": "2024-12-02 14:54:45"
    },
    {
        "id_documento": "12086",
        "pagina": 479,
        "nome_original": "OP 120-2019 - AUTO CIRCUNSTANCIADO - M.pdf",
        "arquivo": "24_2_09032020132120_op1202019autocircunstanciadom.pdf",
        "extensao": ".pdf",
        "pasta": "autocircunstanciado",
        "caminho": "https://10.100.77.20/xpertis/App/Lib/arquivos/documentos/autocircunstanciado/24_2_09032020132120_op1202019autocircunstanciadom.pdf",
        "erro": "Arquivo inexistente",
        "arquivo_existe": 0,
        "data_insercao": "2024-12-02 14:54:45"
    }
]